pysan/__init__.py
pysan/cli.py
pysan/plugin.py
pysan/sanitizer.py
pysan/utils.py
pysan/tests/__init__.py
pysan/tests/conftest.py
pysan/tests/test_utils.py
pytest_sanitizer/__init__.py
pytest_sanitizer/cli.py
pytest_sanitizer/plugin.py
pytest_sanitizer/sanitizer.py
pytest_sanitizer/utils.py
pytest_sanitizer/tests/__init__.py
pytest_sanitizer/tests/conftest.py
pytest_sanitizer/tests/test_utils.py
pytest_sanitizer-0.1.0.dist-info/LICENSE
pytest_sanitizer-0.1.0.dist-info/METADATA
pytest_sanitizer-0.1.0.dist-info/WHEEL
pytest_sanitizer-0.1.0.dist-info/entry_points.txt
pytest_sanitizer-0.1.0.dist-info/top_level.txt
pytest_sanitizer-0.1.0.dist-info/RECORD
